sparksampling_proto/__init__.py
sparksampling_proto/sampling_service_pb2.py
sparksampling_proto/sampling_service_pb2_grpc.py
sparksampling_proto-0.3.0.dist-info/METADATA
sparksampling_proto-0.3.0.dist-info/WHEEL
sparksampling_proto-0.3.0.dist-info/RECORD
