Metadata-Version: 2.1
Name: sparksampling-proto
Version: 0.3.0
Summary: python proto for sparksampling
Project-URL: Source, https://github.com/Wh1isper/pyspark-sampling
Author-email: Wh1isper <9573586@qq.com>
License: BSD 3-Clause License
Keywords: sparksampling
Requires-Python: >=3.8
Requires-Dist: grpcio-tools>=1.15.0
Requires-Dist: grpcio>=1.51.0
Requires-Dist: protobuf>=4
